[
  {
    "arguments": [
      "./build/cross/bin/x86_64-elf-gcc",
      "-std=gnu99",
      "-ffreestanding",
      "-m32",
      "-mno-red-zone",
      "-mno-mmx",
      "-mno-sse",
      "-mno-sse2",
      "-g",
      "-Wall",
      "-Wextra",
      "-Oz",
      "-Iloader/boot1/",
      "-Ilib/",
      "-m32",
      "-g",
      "-c",
      "-o",
      "build/loader/boot1/boot1.o",
      "loader/boot1/boot1.S"
    ],
    "directory": "/mnt/Work/WaddleOS",
    "file": "/mnt/Work/WaddleOS/loader/boot1/boot1.S",
    "output": "/mnt/Work/WaddleOS/build/loader/boot1/boot1.o"
  },
  {
    "arguments": [
      "./build/cross/bin/x86_64-elf-gcc",
      "-std=gnu99",
      "-ffreestanding",
      "-m32",
      "-mno-red-zone",
      "-mno-mmx",
      "-mno-sse",
      "-mno-sse2",
      "-g",
      "-Wall",
      "-Wextra",
      "-Oz",
      "-Iloader/boot1/",
      "-Ilib/",
      "-O3",
      "-m32",
      "-c",
      "-o",
      "build/loader/boot1/lib/serial.o",
      "lib/serial.c"
    ],
    "directory": "/mnt/Work/WaddleOS",
    "file": "/mnt/Work/WaddleOS/lib/serial.c",
    "output": "/mnt/Work/WaddleOS/build/loader/boot1/lib/serial.o"
  },
  {
    "arguments": [
      "./build/cross/bin/x86_64-elf-gcc",
      "-std=gnu99",
      "-ffreestanding",
      "-m32",
      "-mno-red-zone",
      "-mno-mmx",
      "-mno-sse",
      "-mno-sse2",
      "-g",
      "-Wall",
      "-Wextra",
      "-Oz",
      "-Iloader/boot1/",
      "-Ilib/",
      "-O3",
      "-m32",
      "-c",
      "-o",
      "build/loader/boot1/lib/string.o",
      "lib/string.c"
    ],
    "directory": "/mnt/Work/WaddleOS",
    "file": "/mnt/Work/WaddleOS/lib/string.c",
    "output": "/mnt/Work/WaddleOS/build/loader/boot1/lib/string.o"
  },
  {
    "arguments": [
      "./build/cross/bin/x86_64-elf-gcc",
      "-std=gnu99",
      "-ffreestanding",
      "-m32",
      "-mno-red-zone",
      "-mno-mmx",
      "-mno-sse",
      "-mno-sse2",
      "-g",
      "-Wall",
      "-Wextra",
      "-Oz",
      "-Iloader/boot1/",
      "-Ilib/",
      "-O3",
      "-m32",
      "-c",
      "-o",
      "build/loader/boot1/lib/printf.o",
      "lib/printf.c"
    ],
    "directory": "/mnt/Work/WaddleOS",
    "file": "/mnt/Work/WaddleOS/lib/printf.c",
    "output": "/mnt/Work/WaddleOS/build/loader/boot1/lib/printf.o"
  },
  {
    "arguments": [
      "./build/cross/bin/x86_64-elf-gcc",
      "-std=gnu99",
      "-ffreestanding",
      "-m32",
      "-mno-red-zone",
      "-mno-mmx",
      "-mno-sse",
      "-mno-sse2",
      "-g",
      "-Wall",
      "-Wextra",
      "-Oz",
      "-Iloader/boot1/",
      "-Ilib/",
      "-m32",
      "-c",
      "-o",
      "build/loader/boot1/main.o",
      "loader/boot1/main.c"
    ],
    "directory": "/mnt/Work/WaddleOS",
    "file": "/mnt/Work/WaddleOS/loader/boot1/main.c",
    "output": "/mnt/Work/WaddleOS/build/loader/boot1/main.o"
  },
  {
    "arguments": [
      "./build/cross/bin/x86_64-elf-gcc",
      "-std=gnu99",
      "-ffreestanding",
      "-m32",
      "-mno-red-zone",
      "-mno-mmx",
      "-mno-sse",
      "-mno-sse2",
      "-g",
      "-Wall",
      "-Wextra",
      "-Oz",
      "-Iloader/boot1/",
      "-Ilib/",
      "-O3",
      "-m32",
      "-c",
      "-o",
      "build/loader/boot1/lib/term.o",
      "lib/term.c"
    ],
    "directory": "/mnt/Work/WaddleOS",
    "file": "/mnt/Work/WaddleOS/lib/term.c",
    "output": "/mnt/Work/WaddleOS/build/loader/boot1/lib/term.o"
  },
  {
    "arguments": [
      "./build/cross/bin/x86_64-elf-gcc",
      "-std=gnu99",
      "-ffreestanding",
      "-mcmodel=large",
      "-mno-red-zone",
      "-mno-mmx",
      "-mno-sse",
      "-mno-sse2",
      "-g",
      "-Wall",
      "-Wextra",
      "-D__x86_64__",
      "-Ikernel",
      "-Ikernel/drivers",
      "-Ikernel/mem",
      "-Ikernel/sched",
      "-Ilib/",
      "-c",
      "-o",
      "build/kernel/main.o",
      "kernel/main.c"
    ],
    "directory": "/mnt/Work/WaddleOS",
    "file": "/mnt/Work/WaddleOS/kernel/main.c",
    "output": "/mnt/Work/WaddleOS/build/kernel/main.o"
  },
  {
    "arguments": [
      "./build/cross/bin/x86_64-elf-gcc",
      "-std=gnu99",
      "-ffreestanding",
      "-mcmodel=large",
      "-mno-red-zone",
      "-mno-mmx",
      "-mno-sse",
      "-mno-sse2",
      "-g",
      "-Wall",
      "-Wextra",
      "-D__x86_64__",
      "-Ikernel",
      "-Ikernel/drivers",
      "-Ikernel/mem",
      "-Ikernel/sched",
      "-Ilib/",
      "-c",
      "-o",
      "build/kernel/drivers/bitmap.o",
      "kernel/drivers/bitmap.c"
    ],
    "directory": "/mnt/Work/WaddleOS",
    "file": "/mnt/Work/WaddleOS/kernel/drivers/bitmap.c",
    "output": "/mnt/Work/WaddleOS/build/kernel/drivers/bitmap.o"
  },
  {
    "arguments": [
      "./build/cross/bin/x86_64-elf-gcc",
      "-std=gnu99",
      "-ffreestanding",
      "-mcmodel=large",
      "-mno-red-zone",
      "-mno-mmx",
      "-mno-sse",
      "-mno-sse2",
      "-g",
      "-Wall",
      "-Wextra",
      "-D__x86_64__",
      "-Ikernel",
      "-Ikernel/drivers",
      "-Ikernel/mem",
      "-Ikernel/sched",
      "-Ilib/",
      "-c",
      "-o",
      "build/kernel/drivers/idt.o",
      "kernel/drivers/idt.c"
    ],
    "directory": "/mnt/Work/WaddleOS",
    "file": "/mnt/Work/WaddleOS/kernel/drivers/idt.c",
    "output": "/mnt/Work/WaddleOS/build/kernel/drivers/idt.o"
  },
  {
    "arguments": [
      "./build/cross/bin/x86_64-elf-gcc",
      "-std=gnu99",
      "-ffreestanding",
      "-mcmodel=large",
      "-mno-red-zone",
      "-mno-mmx",
      "-mno-sse",
      "-mno-sse2",
      "-g",
      "-Wall",
      "-Wextra",
      "-D__x86_64__",
      "-Ikernel",
      "-Ikernel/drivers",
      "-Ikernel/mem",
      "-Ikernel/sched",
      "-Ilib/",
      "-c",
      "-o",
      "build/kernel/drivers/interrupts.o",
      "kernel/drivers/interrupts.c"
    ],
    "directory": "/mnt/Work/WaddleOS",
    "file": "/mnt/Work/WaddleOS/kernel/drivers/interrupts.c",
    "output": "/mnt/Work/WaddleOS/build/kernel/drivers/interrupts.o"
  },
  {
    "arguments": [
      "./build/cross/bin/x86_64-elf-gcc",
      "-std=gnu99",
      "-ffreestanding",
      "-mcmodel=large",
      "-mno-red-zone",
      "-mno-mmx",
      "-mno-sse",
      "-mno-sse2",
      "-g",
      "-Wall",
      "-Wextra",
      "-D__x86_64__",
      "-Ikernel",
      "-Ikernel/drivers",
      "-Ikernel/mem",
      "-Ikernel/sched",
      "-Ilib/",
      "-c",
      "-o",
      "build/kernel/drivers/multiboot_parser.o",
      "kernel/drivers/multiboot_parser.c"
    ],
    "directory": "/mnt/Work/WaddleOS",
    "file": "/mnt/Work/WaddleOS/kernel/drivers/multiboot_parser.c",
    "output": "/mnt/Work/WaddleOS/build/kernel/drivers/multiboot_parser.o"
  },
  {
    "arguments": [
      "./build/cross/bin/x86_64-elf-gcc",
      "-std=gnu99",
      "-ffreestanding",
      "-mcmodel=large",
      "-mno-red-zone",
      "-mno-mmx",
      "-mno-sse",
      "-mno-sse2",
      "-g",
      "-Wall",
      "-Wextra",
      "-D__x86_64__",
      "-Ikernel",
      "-Ikernel/drivers",
      "-Ikernel/mem",
      "-Ikernel/sched",
      "-Ilib/",
      "-c",
      "-o",
      "build/kernel/drivers/pic.o",
      "kernel/drivers/pic.c"
    ],
    "directory": "/mnt/Work/WaddleOS",
    "file": "/mnt/Work/WaddleOS/kernel/drivers/pic.c",
    "output": "/mnt/Work/WaddleOS/build/kernel/drivers/pic.o"
  },
  {
    "arguments": [
      "./build/cross/bin/x86_64-elf-gcc",
      "-std=gnu99",
      "-ffreestanding",
      "-mcmodel=large",
      "-mno-red-zone",
      "-mno-mmx",
      "-mno-sse",
      "-mno-sse2",
      "-g",
      "-Wall",
      "-Wextra",
      "-D__x86_64__",
      "-Ikernel",
      "-Ikernel/drivers",
      "-Ikernel/mem",
      "-Ikernel/sched",
      "-Ilib/",
      "-c",
      "-o",
      "build/kernel/drivers/pit.o",
      "kernel/drivers/pit.c"
    ],
    "directory": "/mnt/Work/WaddleOS",
    "file": "/mnt/Work/WaddleOS/kernel/drivers/pit.c",
    "output": "/mnt/Work/WaddleOS/build/kernel/drivers/pit.o"
  },
  {
    "arguments": [
      "./build/cross/bin/x86_64-elf-gcc",
      "-std=gnu99",
      "-ffreestanding",
      "-mcmodel=large",
      "-mno-red-zone",
      "-mno-mmx",
      "-mno-sse",
      "-mno-sse2",
      "-g",
      "-Wall",
      "-Wextra",
      "-D__x86_64__",
      "-Ikernel",
      "-Ikernel/drivers",
      "-Ikernel/mem",
      "-Ikernel/sched",
      "-Ilib/",
      "-c",
      "-o",
      "build/kernel/mem/malloc.o",
      "kernel/mem/malloc.c"
    ],
    "directory": "/mnt/Work/WaddleOS",
    "file": "/mnt/Work/WaddleOS/kernel/mem/malloc.c",
    "output": "/mnt/Work/WaddleOS/build/kernel/mem/malloc.o"
  },
  {
    "arguments": [
      "./build/cross/bin/x86_64-elf-gcc",
      "-std=gnu99",
      "-ffreestanding",
      "-mcmodel=large",
      "-mno-red-zone",
      "-mno-mmx",
      "-mno-sse",
      "-mno-sse2",
      "-g",
      "-Wall",
      "-Wextra",
      "-D__x86_64__",
      "-Ikernel",
      "-Ikernel/drivers",
      "-Ikernel/mem",
      "-Ikernel/sched",
      "-Ilib/",
      "-c",
      "-o",
      "build/kernel/mem/paging.o",
      "kernel/mem/paging.c"
    ],
    "directory": "/mnt/Work/WaddleOS",
    "file": "/mnt/Work/WaddleOS/kernel/mem/paging.c",
    "output": "/mnt/Work/WaddleOS/build/kernel/mem/paging.o"
  },
  {
    "arguments": [
      "./build/cross/bin/x86_64-elf-gcc",
      "-std=gnu99",
      "-ffreestanding",
      "-mcmodel=large",
      "-mno-red-zone",
      "-mno-mmx",
      "-mno-sse",
      "-mno-sse2",
      "-g",
      "-Wall",
      "-Wextra",
      "-D__x86_64__",
      "-Ikernel",
      "-Ikernel/drivers",
      "-Ikernel/mem",
      "-Ikernel/sched",
      "-Ilib/",
      "-c",
      "-o",
      "build/kernel/sched/scheduler.o",
      "kernel/sched/scheduler.c"
    ],
    "directory": "/mnt/Work/WaddleOS",
    "file": "/mnt/Work/WaddleOS/kernel/sched/scheduler.c",
    "output": "/mnt/Work/WaddleOS/build/kernel/sched/scheduler.o"
  },
  {
    "arguments": [
      "./build/cross/bin/x86_64-elf-gcc",
      "-std=gnu99",
      "-ffreestanding",
      "-mcmodel=large",
      "-mno-red-zone",
      "-mno-mmx",
      "-mno-sse",
      "-mno-sse2",
      "-g",
      "-Wall",
      "-Wextra",
      "-D__x86_64__",
      "-Ikernel",
      "-Ikernel/drivers",
      "-Ikernel/mem",
      "-Ikernel/sched",
      "-Ilib/",
      "-O3",
      "-c",
      "-o",
      "build/kernel/lib/printf.o",
      "lib/printf.c"
    ],
    "directory": "/mnt/Work/WaddleOS",
    "file": "/mnt/Work/WaddleOS/lib/printf.c",
    "output": "/mnt/Work/WaddleOS/build/kernel/lib/printf.o"
  },
  {
    "arguments": [
      "./build/cross/bin/x86_64-elf-gcc",
      "-std=gnu99",
      "-ffreestanding",
      "-mcmodel=large",
      "-mno-red-zone",
      "-mno-mmx",
      "-mno-sse",
      "-mno-sse2",
      "-g",
      "-Wall",
      "-Wextra",
      "-D__x86_64__",
      "-Ikernel",
      "-Ikernel/drivers",
      "-Ikernel/mem",
      "-Ikernel/sched",
      "-Ilib/",
      "-O3",
      "-c",
      "-o",
      "build/kernel/lib/serial.o",
      "lib/serial.c"
    ],
    "directory": "/mnt/Work/WaddleOS",
    "file": "/mnt/Work/WaddleOS/lib/serial.c",
    "output": "/mnt/Work/WaddleOS/build/kernel/lib/serial.o"
  },
  {
    "arguments": [
      "./build/cross/bin/x86_64-elf-gcc",
      "-std=gnu99",
      "-ffreestanding",
      "-mcmodel=large",
      "-mno-red-zone",
      "-mno-mmx",
      "-mno-sse",
      "-mno-sse2",
      "-g",
      "-Wall",
      "-Wextra",
      "-D__x86_64__",
      "-Ikernel",
      "-Ikernel/drivers",
      "-Ikernel/mem",
      "-Ikernel/sched",
      "-Ilib/",
      "-O3",
      "-c",
      "-o",
      "build/kernel/lib/string.o",
      "lib/string.c"
    ],
    "directory": "/mnt/Work/WaddleOS",
    "file": "/mnt/Work/WaddleOS/lib/string.c",
    "output": "/mnt/Work/WaddleOS/build/kernel/lib/string.o"
  },
  {
    "arguments": [
      "./build/cross/bin/x86_64-elf-gcc",
      "-std=gnu99",
      "-ffreestanding",
      "-mcmodel=large",
      "-mno-red-zone",
      "-mno-mmx",
      "-mno-sse",
      "-mno-sse2",
      "-g",
      "-Wall",
      "-Wextra",
      "-D__x86_64__",
      "-Ikernel",
      "-Ikernel/drivers",
      "-Ikernel/mem",
      "-Ikernel/sched",
      "-Ilib/",
      "-O3",
      "-c",
      "-o",
      "build/kernel/lib/term.o",
      "lib/term.c"
    ],
    "directory": "/mnt/Work/WaddleOS",
    "file": "/mnt/Work/WaddleOS/lib/term.c",
    "output": "/mnt/Work/WaddleOS/build/kernel/lib/term.o"
  },
  {
    "arguments": [
      "./build/cross/bin/x86_64-elf-gcc",
      "-std=gnu99",
      "-ffreestanding",
      "-mcmodel=large",
      "-mno-red-zone",
      "-mno-mmx",
      "-mno-sse",
      "-mno-sse2",
      "-g",
      "-Wall",
      "-Wextra",
      "-D__x86_64__",
      "-Ikernel",
      "-Ikernel/drivers",
      "-Ikernel/mem",
      "-Ikernel/sched",
      "-Ilib/",
      "-c",
      "-o",
      "build/kernel/startup.o",
      "kernel/startup.S"
    ],
    "directory": "/mnt/Work/WaddleOS",
    "file": "/mnt/Work/WaddleOS/kernel/startup.S",
    "output": "/mnt/Work/WaddleOS/build/kernel/startup.o"
  },
  {
    "arguments": [
      "./build/cross/bin/x86_64-elf-gcc",
      "-std=gnu99",
      "-ffreestanding",
      "-mcmodel=large",
      "-mno-red-zone",
      "-mno-mmx",
      "-mno-sse",
      "-mno-sse2",
      "-g",
      "-Wall",
      "-Wextra",
      "-D__x86_64__",
      "-Ikernel",
      "-Ikernel/drivers",
      "-Ikernel/mem",
      "-Ikernel/sched",
      "-Ilib/",
      "-c",
      "-o",
      "build/kernel/drivers/interrupt_stubs.o",
      "kernel/drivers/interrupt_stubs.S"
    ],
    "directory": "/mnt/Work/WaddleOS",
    "file": "/mnt/Work/WaddleOS/kernel/drivers/interrupt_stubs.S",
    "output": "/mnt/Work/WaddleOS/build/kernel/drivers/interrupt_stubs.o"
  }
]
